helloworld.py
helloworld333-0.0.1.dist-info/METADATA
helloworld333-0.0.1.dist-info/WHEEL
helloworld333-0.0.1.dist-info/top_level.txt
helloworld333-0.0.1.dist-info/RECORD
