Metadata-Version: 2.1
Name: helloworld333
Version: 0.0.1
Summary: Say hello
